Metadata-Version: 1.0
Name: asset-allocation-inputs
Version: 0.0.2
Summary: Dash UI component suite
Home-page: UNKNOWN
Author: viv-r
Author-email: UNKNOWN
License: MIT
Platform: UNKNOWN
